gbcms/__init__.py
gbcms/cli.py
gbcms/config.py
gbcms/counter.py
gbcms/models.py
gbcms/numba_counter.py
gbcms/output.py
gbcms/parallel.py
gbcms/processor.py
gbcms/reference.py
gbcms/variant.py
py_gbcms-2.0.0.dist-info/METADATA
py_gbcms-2.0.0.dist-info/WHEEL
py_gbcms-2.0.0.dist-info/entry_points.txt
py_gbcms-2.0.0.dist-info/licenses/LICENSE
py_gbcms-2.0.0.dist-info/RECORD
