Metadata-Version: 2.4
Name: py-gbcms
Version: 2.0.0
Summary: Python implementation of GetBaseCountsMultiSample (gbcms) for calculating base counts in BAM files
Project-URL: Homepage, https://github.com/msk-access/getbasecounts
Project-URL: Repository, https://github.com/msk-access/getbasecounts
Project-URL: Documentation, https://github.com/msk-access/getbasecounts#readme
Project-URL: Bug Tracker, https://github.com/msk-access/getbasecounts/issues
Author-email: MSK-ACCESS <shahr2@mskcc.org>
License: AGPL-3.0
License-File: LICENSE
Keywords: bam,base-counts,bioinformatics,gbcms,genomics,maf,vcf
Classifier: Development Status :: 4 - Beta
Classifier: Intended Audience :: Science/Research
Classifier: License :: OSI Approved :: GNU Affero General Public License v3
Classifier: Programming Language :: Python :: 3.11
Classifier: Programming Language :: Python :: 3.12
Classifier: Topic :: Scientific/Engineering :: Bio-Informatics
Requires-Python: >=3.11
Requires-Dist: joblib>=1.3.0
Requires-Dist: numba>=0.58.0
Requires-Dist: numpy>=1.24.0
Requires-Dist: pandas>=2.0.0
Requires-Dist: pydantic-settings>=2.0.0
Requires-Dist: pydantic>=2.0.0
Requires-Dist: pysam>=0.22.0
Requires-Dist: rich>=13.0.0
Requires-Dist: scipy>=1.11.0
Requires-Dist: typer>=0.9.0
Provides-Extra: all
Requires-Dist: cyvcf2>=0.30.0; extra == 'all'
Provides-Extra: dev
Requires-Dist: black>=23.0.0; extra == 'dev'
Requires-Dist: mypy>=1.5.0; extra == 'dev'
Requires-Dist: pre-commit>=3.3.0; extra == 'dev'
Requires-Dist: pytest-cov>=4.1.0; extra == 'dev'
Requires-Dist: pytest-mock>=3.11.0; extra == 'dev'
Requires-Dist: pytest>=7.4.0; extra == 'dev'
Requires-Dist: ruff>=0.1.0; extra == 'dev'
Requires-Dist: types-pyyaml>=6.0.0; extra == 'dev'
Provides-Extra: fast
Requires-Dist: cyvcf2>=0.30.0; extra == 'fast'
